<?xml version="1.0" encoding="UTF-8" ?><root><rating type="float">3.8</rating><votes type="str">26</votes><title type="str">The Missing Dog!</title><url type="str">http://www.greatcleanjokes.com/3956/missing-dog/</url><content type="null"></content><comments_count type="str">2</comments_count><id type="str">132</id><categories type="list"><item type="dict"><subcategory_id type="str">131</subcategory_id><category_id type="str">118</category_id><subcategory_name type="str">Funny Pictures</subcategory_name><category_name type="str">Fun Stuff</category_name></item><item type="dict"><subcategory_id type="str">179</subcategory_id><category_id type="str">126</category_id><subcategory_name type="str">Dog Jokes</subcategory_name><category_name type="str">Pet Jokes</category_name></item></categories></root>