{"rating": 4.3, "votes": 19, "title": "Men? Fathers?", "url": "http://www.greatcleanjokes.com/539/men-fathers-men-joke/", "content": "A couple had their first baby. After a week or so the mother thought she could use a break and went shopping leaving the little baby with the proud father. It was only a short while before the baby started to cry. The perplexed father tried all of the tricks that he remembered his wife doing but to no avail. Finally after a half hour  in desperation he went to the doctor. After checking all of the regular things the doctor  discovered it was just a dirty diaper.", "comments_count": 1, "id": 448, "categories": [{"subcategory_id": "171", "category_id": "124", "subcategory_name": "Long Jokes", "category_name": "Other Joke Types"}, {"subcategory_id": "174", "category_id": "125", "subcategory_name": "Men Jokes", "category_name": "People Jokes"}]}