{"rating": 3.7, "votes": 45, "title": "Hypochondriac Joke", "url": "http://www.greatcleanjokes.com/3482/hypochondriac-joke/", "content": "Brian, one of the worlds greatest hypochondriacs, bumped into his Dr. one day at the supermarket.  ", "comments_count": 1, "id": 49, "categories": [{"subcategory_id": "120", "category_id": "116", "subcategory_name": "Doctor Jokes", "category_name": "Doctor Humor"}, {"subcategory_id": "122", "category_id": "116", "subcategory_name": "Medical Jokes", "category_name": "Doctor Humor"}]}