<?xml version="1.0" encoding="UTF-8"?>
<root>
    <rating type="float">3.3</rating>
    <votes type="str">165</votes>
    <title type="str">The Forgetful Actor</title>
    <url type="str">http://www.greatcleanjokes.com/143/funny-speach-opener/</url>
    <content type="str">An actor had been out of work for 15 years because he always forgot his lines. Then one day he got a phone call from a director who wanted him for a big part in a play. All he had to say was “Hark! I hear the cannon roar! After much worry the actor decided to take  the role. Opening night arrived, and while he waited in the wings, the actor muttered to himself “Hark! I hear the cannon roar! Hark! I hear the cannon roar! The time for the entrance finally came and as the actor made his appearance, he heard a loud brooooom! He turned around and said, “what the hell was that?” -Robert De Nero
</content>
    <comments_count type="str">4</comments_count>
    <id type="str">8</id>
    <categories type="list">
        <item type="dict">
            <subcategory_id type="str">112</subcategory_id>
            <category_id type="str">113</category_id>
            <subcategory_name type="str">Good Jokes</subcategory_name>
            <category_name type="str">Best Jokes</category_name>
        </item>
        <item type="dict">
            <subcategory_id type="str">167</subcategory_id>
            <category_id type="str">124</category_id>
            <subcategory_name type="str">Funny Speech Openers</subcategory_name>
            <category_name type="str">Other Joke Types</category_name>
        </item>
        <item type="dict">
            <subcategory_id type="str">171</subcategory_id>
            <category_id type="str">124</category_id>
            <subcategory_name type="str">Long Jokes</subcategory_name>
            <category_name type="str">Other Joke Types</category_name>
        </item>
    </categories>
    <length type="str">596</length>
    <POS_histogram type="str">0.047,0.25,0.016,0.016,0.047,0.0,0.063,0.0,0.0,0.047,0.0,0.0,0.391,0.047,0.078,0.0,</POS_histogram>
    <QA type="str">0</QA>
    <nouns_with_sexual_connotations type="str">0.0</nouns_with_sexual_connotations>
    <nouns_with_multiple_meanings type="str">0.818</nouns_with_multiple_meanings>
    <verbs_with_sexual_connotations type="str">0.167</verbs_with_sexual_connotations>
    <verbs_with_multiple_meanings type="str">0.958</verbs_with_multiple_meanings>
    <adjectives_with_sexual_connotations type="str">0.0</adjectives_with_sexual_connotations>
    <adjectives_with_multiple_meanings type="str">1.0</adjectives_with_multiple_meanings>
    <adverbs_with_sexual_connotations type="str">0.0</adverbs_with_sexual_connotations>
    <adverbs_with_multiple_meanings type="str">0.333</adverbs_with_multiple_meanings>
    <professional_communities_histogram type="str">0,2,3,</professional_communities_histogram>
    <racist_slur type="str">0.0</racist_slur>
    <sexism type="str">0.0</sexism>
    <simple_POS_histo type="str">0.516,0.375,0.063,0.047,</simple_POS_histo>
    <insulting type="str">0.0</insulting>
    <quote type="str">0.287</quote>
</root>
